pysched_lightning/__init__.py
pysched_lightning/executor.py
pysched_lightning/queue.py
pysched_lightning/scheduler.py
pysched_lightning/task.py
pysched_lightning/trigger.py
PySched_Lightning-0.1.1.dist-info/LICENSE
PySched_Lightning-0.1.1.dist-info/METADATA
PySched_Lightning-0.1.1.dist-info/WHEEL
PySched_Lightning-0.1.1.dist-info/top_level.txt
PySched_Lightning-0.1.1.dist-info/RECORD
